{
  "fileUpload": {
    "clearFiles": "[ZH:clearFiles]",
    "imageSizeExceeded": "[ZH:imageSizeExceeded]",
    "maxFilesReached": "[ZH:maxFilesReached]",
    "networkError": "[ZH:networkError]",
    "selectImage": "[ZH:selectImage]",
    "selectVideo": "[ZH:selectVideo]",
    "sizeExceeded": "[ZH:sizeExceeded]",
    "supportAllSize": "[ZH:supportAllSize]",
    "supportFormat": "[ZH:supportFormat]",
    "unsupportedType": "[ZH:unsupportedType]",
    "uploadFailed": "[ZH:uploadFailed]",
    "uploadSuccess": "[ZH:uploadSuccess]",
    "uploading": "[ZH:uploading]",
    "videoSizeExceeded": "[ZH:videoSizeExceeded]"
  }
}
